odoo10_addon_attachment_edit-10.0.1.0.0.99.dev3-py3.8-nspkg.pth
odoo/addons/attachment_edit/README.rst
odoo/addons/attachment_edit/__init__.py
odoo/addons/attachment_edit/__manifest__.py
odoo/addons/attachment_edit/i18n/attachment_edit.pot
odoo/addons/attachment_edit/i18n/de.po
odoo/addons/attachment_edit/i18n/it.po
odoo/addons/attachment_edit/i18n/sl.po
odoo/addons/attachment_edit/i18n/zh_CN.po
odoo/addons/attachment_edit/models/__init__.py
odoo/addons/attachment_edit/models/ir_attachment.py
odoo/addons/attachment_edit/readme/CONTRIBUTORS.rst
odoo/addons/attachment_edit/readme/DESCRIPTION.rst
odoo/addons/attachment_edit/readme/USAGE.rst
odoo/addons/attachment_edit/static/description/icon.png
odoo/addons/attachment_edit/static/description/index.html
odoo/addons/attachment_edit/static/src/js/attachment_edit.js
odoo/addons/attachment_edit/static/src/xml/attachment_edit.xml
odoo/addons/attachment_edit/tests/__init__.py
odoo/addons/attachment_edit/tests/test_attachment_edit.py
odoo/addons/attachment_edit/views/ir_attachment.xml
odoo/addons/attachment_edit/views/templates.xml
odoo10_addon_attachment_edit-10.0.1.0.0.99.dev3.dist-info/METADATA
odoo10_addon_attachment_edit-10.0.1.0.0.99.dev3.dist-info/WHEEL
odoo10_addon_attachment_edit-10.0.1.0.0.99.dev3.dist-info/namespace_packages.txt
odoo10_addon_attachment_edit-10.0.1.0.0.99.dev3.dist-info/top_level.txt
odoo10_addon_attachment_edit-10.0.1.0.0.99.dev3.dist-info/RECORD
